datadash/__init__.py
datadash/__main__.py
datadash-0.0.4.dist-info/METADATA
datadash-0.0.4.dist-info/WHEEL
datadash-0.0.4.dist-info/licenses/LICENSE
datadash-0.0.4.dist-info/RECORD
