Metadata-Version: 2.3
Name: Datadash
Version: 0.0.4
Summary: Taking a quick look at data.
Project-URL: Homepage, https://github.com/galenseilis/datadash
Project-URL: Issues, https://github.com/galenseilis/datadash/issues
Author-email: Galen Seilis <galen.seilis@seilis.ca>
License-File: LICENSE
Classifier: License :: OSI Approved :: MIT License
Classifier: Operating System :: OS Independent
Classifier: Programming Language :: Python :: 3
Requires-Python: >=3.8
